{
  "Instanties": [
    {
      "PublicerendeInstantieOmschrijving": "Rechtbank Amsterdam",
      "Locaties": [
        {
          "LocatiecodeLocatie": null,
          "Straat": "Parnassusweg",
          "Huisnummer": "220",
          "HuisnummerToevoeging": null,
          "PlaatsNaam": null
        }
      ],
      "Publicatieclusters": [
        {
          "PublicatieclusterOmschrijving": "zittingen in faillissementen",
          "Publicatiesoorten": [
            {
              "PublicatiesoortCaption": "verificatievergadering",
              "PublicatiesNaarLocatie": [
                {
                  "LocatiecodeBekendmaking": null,
                  "Publicaties": [
                    "verificatievergadering: pro forma op 24 september 2020 om 9:25 uur inzake (F.13/18/291) Petenia Patricia SCHAKEN, woonadr. Harmonielaan 43, 1111 PD Diemen, geb. distrikt Suriname (Suriname) 24 november 1967. Cur: M. van Rijswijk, Postbus 75727, 1070 AS Amsterdam, tel. 020-3052030. Uiterste datum van indiening vorderingen: 10 september 2020."
                  ]
                }
              ]
            }
          ]
        },
        {
          "PublicatieclusterOmschrijving": "einde schuldsaneringen",
          "Publicatiesoorten": [
            {
              "PublicatiesoortCaption": "zonder uitdeling en zonder schone lei",
              "PublicatiesNaarLocatie": [
                {
                  "LocatiecodeBekendmaking": null,
                  "Publicaties": [
                    "zonder uitdeling en zonder schone lei: op 19 februari 2020 inzake (R.13/19/295) Luz Karime DIAZ LARREA, woonadr. Marathonweg 70 1, 1076 TM Amsterdam, geb. Cali Valle (Colombia) 27 april 1981."
                  ]
                }
              ]
            }
          ]
        }
      ]
    },
    {
      "PublicerendeInstantieOmschrijving": "Rechtbank Den Haag",
      "Locaties": [
        {
          "LocatiecodeLocatie": null,
          "Straat": "Prins Clauslaan",
          "Huisnummer": "60",
          "HuisnummerToevoeging": null,
          "PlaatsNaam": null
        }
      ],
      "Publicatieclusters": [
        {
          "PublicatieclusterOmschrijving": "zittingen in schuldsaneringen",
          "Publicatiesoorten": [
            {
              "PublicatiesoortCaption": "beëindigingszitting",
              "PublicatiesNaarLocatie": [
                {
                  "LocatiecodeBekendmaking": null,
                  "Publicaties": [
                    "beëindigingszitting: op 24 augustus 2020 inzake (R.9/17/144) Johannes Wilhelmus Floyd Meulenbeld, woonadr. Pasteurstraat 165, 2522 RH Den Haag, geb. 's-Hertogenbosch Nederland 24 mei 1991. Bwv: H.A. Thomason (Equalis Bewindvoering), Postbus 12, 3214 ZG Zuidland, tel. 0181-699300."
                  ]
                }
              ]
            }
          ]
        }
      ]
    },
    {
      "PublicerendeInstantieOmschrijving": "Rechtbank Gelderland",
      "Locaties": [
        {
          "LocatiecodeLocatie": "Arnhem",
          "Straat": "Walburgstraat",
          "Huisnummer": "2-4",
          "HuisnummerToevoeging": "",
          "PlaatsNaam": "Arnhem"
        },
        {
          "LocatiecodeLocatie": "Zutphen",
          "Straat": "Martinetsingel",
          "Huisnummer": "2",
          "HuisnummerToevoeging": "",
          "PlaatsNaam": "Zutphen"
        }
      ],
      "Publicatieclusters": [
        {
          "PublicatieclusterOmschrijving": "uitspraken faillissement",
          "Publicatiesoorten": [
            {
              "PublicatiesoortCaption": null,
              "PublicatiesNaarLocatie": [
                {
                  "LocatiecodeBekendmaking": null,
                  "Publicaties": [
                    "Uitspraak faillissement op 03 augustus 2020 inzake (F.05/20/277) Collis Warehousing & Distribution B.V, vest.adr. De Iepenwei 7 4191PD Geldermalsen, KvK: 67982301 hodn Collis Warehousing & Distribution B.V. corr.adr. De Iepenwei 7 4191PD Geldermalsen, vest.adr. De Iepenwei 7 4191PD Geldermalsen. Cur: mr J.M.A.J. Thielen, Postbus 124 4000AC TIEL tel. 0344-677188. RC: mr. E Boerwinkel."
                  ]
                }
              ]
            }
          ]
        },
        {
          "PublicatieclusterOmschrijving": "einde faillissementen",
          "Publicatiesoorten": [
            {
              "PublicatiesoortCaption": "door verbindende uitdelingslijst",
              "PublicatiesNaarLocatie": [
                {
                  "LocatiecodeBekendmaking": null,
                  "Publicaties": [
                    "Door verbindende uitdelingslijst op 04 augustus 2020 inzake (F.05/16/264) Bouwservice Plus B.V, vest.adr. Meerval 13 3892HW Zeewolde, KvK: 57177937.",
                    "Door verbindende uitdelingslijst op 04 augustus 2020 inzake (F.05/17/611) Kadmos Kolsloot B.V, vest.adr. Stationsweg 46 6861EJ Oosterbeek, KvK: 63057476.",
                    "Door verbindende uitdelingslijst op 04 augustus 2020 inzake (F.05/18/74) E@Britain B.V, corr.adr. Postbus 18 6666ZG Heteren, vest.adr. P v M Gelderland Blauw 8 a 6666LR Heteren, KvK: 09204528.",
                    "Door verbindende uitdelingslijst op 04 augustus 2020 inzake (F.05/18/454) 5R Medication Management B.V, vest.adr. Lingewei 57 4004LK Tiel, KvK: 66504775 hodn 5R Medication Management B.V. corr.adr. Lingewei 57 4004LK Tiel, vest.adr. Lingewei 57 4004LK Tiel.",
                    "Door verbindende uitdelingslijst op 04 augustus 2020 inzake (F.05/18/491) Dakbedekkingsbedrijf Eldo B.V, vest.adr. Stek 10 3371KG Hardinxveld-Giessendam, KvK: 24343481 hodn Dakbedekkingsbedrijf Eldo B.V. corr.adr. Stek 10 3371KG Hardinxveld-Giessendam, vest.adr. Stek 10 3371KG Hardinxveld-Giessendam.",
                    "Door verbindende uitdelingslijst op 04 augustus 2020 inzake (F.05/19/285) Lingerie Odendaal Nijmegen B.V, vest.adr. Passage Molenpoort 118 6511HX Nijmegen, KvK: 09132380 hodn Lingerie Odendaal Nijmegen B.V. corr.adr. Passage Molenpoort 118 6511HX Nijmegen, vest.adr. Passage Molenpoort 118 6511HX Nijmegen.",
                    "Door verbindende uitdelingslijst op 04 augustus 2020 inzake (F.05/19/385) De Gezonde Leefstijl B.V, vest.adr. Guldenweg 1 a 7051HT VARSSEVELD, KvK: 69392471 hodn De Gezonde Leefstijl B.V. corr.adr. Guldenweg 1 a 7051HT VARSSEVELD, vest.adr. Guldenweg 1 a 7051HT VARSSEVELD, hodn Fit in corr.adr. Guldenweg 1 a 7051HT VARSSEVELD, vest.adr. Guldenweg 1 a 7051HT VARSSEVELD, hodn Fit in Varsseveld corr.adr. Guldenweg 1 a 7051HT VARSSEVELD, vest.adr. Guldenweg 1 a 7051HT VARSSEVELD."
                  ]
                }
              ]
            }
          ]
        }
      ]
    },
    {
      "PublicerendeInstantieOmschrijving": "Rechtbank Limburg",
      "Locaties": [
        {
          "LocatiecodeLocatie": "Maastricht",
          "Straat": "St. Annadal",
          "Huisnummer": "1",
          "HuisnummerToevoeging": null,
          "PlaatsNaam": "Maastricht"
        },
        {
          "LocatiecodeLocatie": "Roermond",
          "Straat": "Willem II Singel",
          "Huisnummer": "67",
          "HuisnummerToevoeging": null,
          "PlaatsNaam": "Roermond"
        }
      ],
      "Publicatieclusters": [
        {
          "PublicatieclusterOmschrijving": "neerlegging slotuitdelingslijst in faillissementen",
          "Publicatiesoorten": [
            {
              "PublicatiesoortCaption": null,
              "PublicatiesNaarLocatie": [
                {
                  "LocatiecodeBekendmaking": "Maastricht",
                  "Publicaties": [
                    "Met ingang van 03 augustus 2020 inzake (F.03/11/14) L.I.E.L. Opreij, geb. Maastricht 25 januari 1967."
                  ]
                }
              ]
            }
          ]
        },
        {
          "PublicatieclusterOmschrijving": "einde faillissementen",
          "Publicatiesoorten": [
            {
              "PublicatiesoortCaption": "wegens gebrek aan baten",
              "PublicatiesNaarLocatie": [
                {
                  "LocatiecodeBekendmaking": null,
                  "Publicaties": [
                    "Wegens gebrek aan baten op 04 augustus 2020 inzake (F.03/17/177) Inco+ B.V, vest.adr. Putgraaf 3 6411GT Heerlen, KvK: 14081432.",
                    "Wegens gebrek aan baten op 04 augustus 2020 inzake (F.03/17/178) Holding Mar+ B.V, vest.adr. Putgraaf 3 6411GT Heerlen, KvK: 14116239.",
                    "Wegens gebrek aan baten op 04 augustus 2020 inzake (F.03/17/179) De TWEE Gezusters - centrum voor diversiteit B.V, vest.adr. Putgraaf 3 6411GT Heerlen, KvK: 14116258.",
                    "Wegens gebrek aan baten op 04 augustus 2020 inzake (F.03/17/180) De Twee gezusters - Horeca B.V, vest.adr. Putgraaf 3 6411GT Heerlen, KvK: 14121411.",
                    "Wegens gebrek aan baten op 04 augustus 2020 inzake (F.03/18/37) M.A.T. Kicken, woonadr. Antoon van Elenstraat 32 B 6217JM Maastricht, geb. Valkenburg-Houthem (Nederland) 07 januari 1956. hodn Kicken! vest.adr. Tongersestraat 9 6211LL Maastricht, KvK: 61885118.",
                    "Wegens gebrek aan baten op 04 augustus 2020 inzake (F.03/19/235) Mito Medical Products B.V, vest.adr. Sint Jansweg 20 5928RC Venlo, KvK: 64783898 hodn Mito Medical Products B.V. corr.adr. Sint Jansweg 20 5928RC Venlo, vest.adr. Sint Jansweg 20 5928RC Venlo."
                  ]
                }
              ]
            }
          ]
        }
      ]
    },
    {
      "PublicerendeInstantieOmschrijving": "Rechtbank Midden-Nederland",
      "Locaties": [
        {
          "LocatiecodeLocatie": "Almere",
          "Straat": "De Diagonaal",
          "Huisnummer": "37",
          "HuisnummerToevoeging": null,
          "PlaatsNaam": "Almere"
        },
        {
          "LocatiecodeLocatie": "Lelystad",
          "Straat": "Stationsplein",
          "Huisnummer": "15",
          "HuisnummerToevoeging": null,
          "PlaatsNaam": "Lelystad"
        },
        {
          "LocatiecodeLocatie": "Utrecht",
          "Straat": "Vrouwe Justitiaplein",
          "Huisnummer": "1",
          "HuisnummerToevoeging": null,
          "PlaatsNaam": "Utrecht"
        }
      ],
      "Publicatieclusters": [
        {
          "PublicatieclusterOmschrijving": "zittingen in faillissementen",
          "Publicatiesoorten": [
            {
              "PublicatiesoortCaption": "verificatievergadering",
              "PublicatiesNaarLocatie": [
                {
                  "LocatiecodeBekendmaking": "Utrecht",
                  "Publicaties": [
                    "Verificatievergadering: pro forma op 08 oktober 2020 om 9:00 uur inzake (F.16/18/523), Stichts Handelshuis Badkamers B.V, vest.adr. Zonnebaan 36 3542EE Utrecht, KvK: 30139974 hodn Stichts Handelshuis Badkamers B.V. corr.adr. Zonnebaan 36 3542EE Utrecht, vest.adr. Zonnebaan 36 3542EE Utrecht, hodn Stichts Handelshuis Sanitair corr.adr. Zonnebaan 36 3542EE Utrecht, vest.adr. Zonnebaan 36 3542EE Utrecht, hodn Stichts Handelshuis Badkamers corr.adr. Zonnebaan 36 3542EE Utrecht, vest.adr. Zonnebaan 36 3542EE Utrecht, hodn Sanitair Outlet Maarssen corr.adr. Zonnebaan 36 3542EE Utrecht, vest.adr. Zonnebaan 36 3542EE Utrecht. Cur: mr M.J. Guit, Postbus 69.111 1060CD AMSTERDAM tel. 035-3020015. Uiterste datum van indiening vorderingen: 24 september 2020."
                  ]
                }
              ]
            }
          ]
        },
        {
          "PublicatieclusterOmschrijving": "zittingen in schuldsaneringen",
          "Publicatiesoorten": [
            {
              "PublicatiesoortCaption": "beëindigingszitting",
              "PublicatiesNaarLocatie": [
                {
                  "LocatiecodeBekendmaking": "Lelystad",
                  "Publicaties": [
                    "Beëindigingszitting op 10 september 2020 om 9:00 uur inzake (R.16/17/585), P.G.M. Steenvoorden, geb. Nieuwer-Amstel (Nederland) 10 augustus 1956. Bwv: M.W. van Dijk-Middelweerd (Bewindvoering Midden Nederland), Hessenweg 180 3731JN De Bilt tel. 030-2724444.",
                    "Beëindigingszitting op 05 november 2020 om 9:00 uur inzake (R.16/17/697), A.J. Mussendijk, woonadr. Korte Promenade 29 1315HM Almere, geb. Paramaribo (Suriname) 19 augustus 1953. Bwv: F.J. Velner (Schuldsanering Flevoland B.V.), Meenthoek 7 8224BS Lelystad tel. 0320 234828."
                  ]
                }
              ]
            },
            {
              "PublicatiesoortCaption": "verificatievergadering",
              "PublicatiesNaarLocatie": [
                {
                  "LocatiecodeBekendmaking": "Lelystad",
                  "Publicaties": [
                    "Verificatievergadering: pro forma op 07 september 2020 om 11:00 uur inzake (R.16/17/585), P.G.M. Steenvoorden, geb. Nieuwer-Amstel (Nederland) 10 augustus 1956. Bwv: M.W. van Dijk-Middelweerd (Bewindvoering Midden Nederland), Hessenweg 180 3731JN De Bilt tel. 030-2724444.",
                    "Verificatievergadering: pro forma op 28 september 2020 om 11:00 uur inzake (R.16/17/669), S.J. van der Meij, woonadr. Daltonstraat 144 1223RR Hilversum, geb. Mulago (Uganda) 26 juni 1976. voorheen hodn The Oak Table Writers vest.adr. Kapelstraat 42 1211LZ Hilversum, KvK: 64789942. Bwv: M.W. van Dijk-Middelweerd (Bewindvoering Midden Nederland), Hessenweg 180 3731JN De Bilt tel. 030-2724444.",
                    "Verificatievergadering: pro forma op 26 oktober 2020 om 11:00 uur inzake (R.16/17/697), A.J. Mussendijk, woonadr. Korte Promenade 29 1315HM Almere, geb. Paramaribo (Suriname) 19 augustus 1953. Bwv: F.J. Velner (Schuldsanering Flevoland B.V.), Meenthoek 7 8224BS Lelystad tel. 0320 234828."
                  ]
                }
              ]
            }
          ]
        },
        {
          "PublicatieclusterOmschrijving": "neerlegging slotuitdelingslijst in faillissementen",
          "Publicatiesoorten": [
            {
              "PublicatiesoortCaption": null,
              "PublicatiesNaarLocatie": [
                {
                  "LocatiecodeBekendmaking": "Utrecht",
                  "Publicaties": [
                    "Met ingang van 25 augustus 2020 inzake (F.16/15/373) Privilege B.V, vest.adr. Rading 2 a 1231KA Loosdrecht, KvK: 09125644.",
                    "Met ingang van 25 augustus 2020 inzake (F.16/15/864) J&D Investments holding B.V, corr.adr. Postbus 1 3755ZG Eemnes, vest.adr. Bramenberg 9 5 3755BT Eemnes, KvK: 22035208.",
                    "Met ingang van 25 augustus 2020 inzake (F.16/16/410) Meurs Werkt B.V, corr.adr. Postbus 97 3440AB Woerden, vest.adr. De Bleek 10 3447GV Woerden, KvK: 30196619 hodn Meurs Werkt!.",
                    "Met ingang van 25 augustus 2020 inzake (F.16/18/86) Taxi Eemland Personenvervoer B.V, vest.adr. Eikenlaan 5 3768ES Soest, KvK: 32106429.",
                    "Met ingang van 25 augustus 2020 inzake (F.16/18/93) E.M. Oumghar, woonadr. Satijnvlinder 51 3544VX Utrecht, geb. Meknès (Marokko) 23 oktober 1972. hodn Guel Clothes vest.adr. Catharijnesingel 66 D 3511GK Utrecht, KvK: 30148900.",
                    "Met ingang van 25 augustus 2020 inzake (F.16/18/277) P. van Gellekom, woonadr. Chalonhof 18 3762CS Soest, geb. Amersfoort 15 januari 1971. hodn Gellekom 4x4 vest.adr. Nijerheidsweg 7 3762EP Soest, KvK: 51965739, hodn G-Trading vest.adr. Nijverheidsweg 7 3762EP Soest, KvK: 51965739, hodn MotivEmotion vest.adr. Nijverheidsweg 7 3762EP Soest, KvK: 51965739.",
                    "Met ingang van 25 augustus 2020 inzake (F.16/18/415) Teuwissen Installatie Groep B.V, vest.adr. Koningsweg 2 17 3762EC Soest, KvK: 32108995 hodn Teuwissen Installatie Groep B.V. corr.adr. Koningsweg 2 17 3762EC Soest, vest.adr. Koningsweg 2 17 3762EC Soest, hodn Teuwissen Technisch Bedrijf corr.adr. Koningsweg 2 17 3762EC Soest, vest.adr. Koningsweg 2 17 3762EC Soest, hodn Teuwissen Installatietechniek corr.adr. Koningsweg 2 17 3762EC Soest, vest.adr. Koningsweg 2 17 3762EC Soest.",
                    "Met ingang van 25 augustus 2020 inzake (F.16/19/9) Maxx aanhuurmakelaars Utrecht B.V, vest.adr. Nachtegaalstraat 3 3581AA Utrecht, KvK: 66718198 hodn Maxx aanhuurmakelaars Utrecht B.V. corr.adr. Nachtegaalstraat 3 3581AA Utrecht, vest.adr. Nachtegaalstraat 3 3581AA Utrecht.",
                    "Met ingang van 25 augustus 2020 inzake (F.16/19/126) NEXOR B.V, vest.adr. Lange Dreef 15 d 4131NJ Vianen, KvK: 18062293 hodn NEXOR B.V. corr.adr. Lange Dreef 15 d 4131NJ Vianen, vest.adr. Lange Dreef 15 d 4131NJ Vianen, hodn NEXOR corr.adr. Lange Dreef 15 d 4131NJ Vianen, vest.adr. Lange Dreef 15 d 4131NJ Vianen."
                  ]
                }
              ]
            }
          ]
        },
        {
          "PublicatieclusterOmschrijving": "einde faillissementen",
          "Publicatiesoorten": [
            {
              "PublicatiesoortCaption": "vernietiging faillissement na verzet",
              "PublicatiesNaarLocatie": [
                {
                  "LocatiecodeBekendmaking": null,
                  "Publicaties": [
                    "Vernietiging faillissement na verzet op 23 juli 2020 inzake (F.16/20/255) Peters Equipment B.V, vest.adr. Dolderseweg 94 3734BK Den Dolder, KvK: 30166071 hodn Peters Equipment B.V. corr.adr. Dolderseweg 94 3734BK Den Dolder, vest.adr. Dolderseweg 94 3734BK Den Dolder."
                  ]
                }
              ]
            }
          ]
        }
      ]
    },
    {
      "PublicerendeInstantieOmschrijving": "Rechtbank Noord-Holland",
      "Locaties": [
        {
          "LocatiecodeLocatie": "Alkmaar",
          "Straat": "Kruseman van Eltenweg",
          "Huisnummer": "2",
          "HuisnummerToevoeging": null,
          "PlaatsNaam": "Alkmaar"
        },
        {
          "LocatiecodeLocatie": "Haarlem",
          "Straat": "Jansstraat",
          "Huisnummer": "81",
          "HuisnummerToevoeging": null,
          "PlaatsNaam": "Haarlem"
        }
      ],
      "Publicatieclusters": [
        {
          "PublicatieclusterOmschrijving": "uitspraken faillissement",
          "Publicatiesoorten": [
            {
              "PublicatiesoortCaption": "door tussentijdse beëindiging schuldsanering",
              "PublicatiesNaarLocatie": [
                {
                  "LocatiecodeBekendmaking": null,
                  "Publicaties": [
                    "Uitspraak faillissement door tussentijdse beëindiging schuldsanering op 30 juli 2020 inzake (F.15/20/238, was R.15/15/1025) H.J.H. Luik, woonadr. Beukenlaan 12 1766JH Wieringerwaard, geb. Den Helder (Nederland) 14 juli 1965. Cur: mr B.J. Mekkelholt, Luchthavenweg 16 1786PP DEN HELDER tel. 0223-660114. RC: mr. J.J. Dijk."
                  ]
                }
              ]
            }
          ]
        },
        {
          "PublicatieclusterOmschrijving": "zittingen in faillissementen",
          "Publicatiesoorten": [
            {
              "PublicatiesoortCaption": "verificatievergadering",
              "PublicatiesNaarLocatie": [
                {
                  "LocatiecodeBekendmaking": "Alkmaar",
                  "Publicaties": [
                    "Verificatievergadering: pro forma op 28 september 2020 om 0:00 uur inzake (F.14/13/1), De Graaf Autospuitbedrijf B.V, vest.adr. De Buurt 114 1606AJ Venhuizen, KvK: 36018224. Cur: mr K.A. Cerutti, Grote Oost 6 1621BW HOORN NH tel. 0229-287000. Uiterste datum van indiening vorderingen: 14 september 2020."
                  ]
                }
              ]
            }
          ]
        }
      ]
    },
    {
      "PublicerendeInstantieOmschrijving": "Rechtbank Noord-Nederland",
      "Locaties": [
        {
          "LocatiecodeLocatie": "Assen",
          "Straat": "Brinkstraat",
          "Huisnummer": "4",
          "HuisnummerToevoeging": null,
          "PlaatsNaam": "Assen"
        },
        {
          "LocatiecodeLocatie": "Groningen",
          "Straat": "Guyotplein",
          "Huisnummer": "1",
          "HuisnummerToevoeging": null,
          "PlaatsNaam": "Groningen"
        },
        {
          "LocatiecodeLocatie": "Leeuwarden",
          "Straat": "Zaailand",
          "Huisnummer": "102",
          "HuisnummerToevoeging": null,
          "PlaatsNaam": "Leeuwarden"
        }
      ],
      "Publicatieclusters": [
        {
          "PublicatieclusterOmschrijving": "zittingen in schuldsaneringen",
          "Publicatiesoorten": [
            {
              "PublicatiesoortCaption": "beëindigingszitting",
              "PublicatiesNaarLocatie": [
                {
                  "LocatiecodeBekendmaking": "Groningen",
                  "Publicaties": [
                    "beëindigingszitting: op 21 augustus 2020 om 16:00 uur inzake (R.18/17/667) Charlotte Daniëlle van Dalen, woonadr. Thorbeckestraat 59, 9801 KB Zuidhorn, geb. Groningen 11 november 1984. Bwv: W. de Haan, Postbus 3036, 9701 DA Groningen, tel. 050-7114012.",
                    "beëindigingszitting: op 04 september 2020 inzake (R.18/17/722) Marius Uiltje Johan Leo Jeeninga, woonadr. Van der Munniklaan 17, 9965 RP Leens, geb. Leeuwarden 04 november 1969. Bwv: J.M. Niemeijer, Postbus 1374, 9701 BJ Groningen, tel. 050-3135154."
                  ]
                }
              ]
            }
          ]
        },
        {
          "PublicatieclusterOmschrijving": "neerlegging slotuitdelingslijst in schuldsaneringen",
          "Publicatiesoorten": [
            {
              "PublicatiesoortCaption": null,
              "PublicatiesNaarLocatie": [
                {
                  "LocatiecodeBekendmaking": "Assen",
                  "Publicaties": [
                    "met ingang van 18 augustus 2020 inzake (R.18/17/534) Danny Klok, woonadr. Wilgenroos 60, 9461 LE Gieten, geb. Stadskanaal 16 september 1986."
                  ]
                }
              ]
            }
          ]
        },
        {
          "PublicatieclusterOmschrijving": "einde faillissementen",
          "Publicatiesoorten": [
            {
              "PublicatiesoortCaption": "wegens gebrek aan baten",
              "PublicatiesNaarLocatie": [
                {
                  "LocatiecodeBekendmaking": null,
                  "Publicaties": [
                    "Wegens gebrek aan baten op 04 augustus 2020 inzake (F.17/13/348) J.B.A.N. Beheer B.V, vest.adr. Nieuwstad 44 9251LN Burgum, KvK: 01094235.",
                    "Wegens gebrek aan baten op 04 augustus 2020 inzake (F.17/15/63) De Jong Jirnsum B.V, vest.adr, KvK: 01092726.",
                    "Wegens gebrek aan baten op 04 augustus 2020 inzake (F.17/18/26) Maple Skate B.V, vest.adr. De Kuinder 1 8444DC Heerenveen, KvK: 04038664 hodn MAPLEZ Racing Sports."
                  ]
                }
              ]
            },
            {
              "PublicatiesoortCaption": "door verbindende uitdelingslijst",
              "PublicatiesNaarLocatie": [
                {
                  "LocatiecodeBekendmaking": null,
                  "Publicaties": [
                    "Door verbindende uitdelingslijst op 31 juli 2020 inzake (F.18/19/198) Groningen Containerverhuur B.V, vest.adr. Australiëweg 4 9407TE Assen, KvK: 73342912 hodn Groningen Containerverhuur B.V. corr.adr. Australiëweg 4 9407TE Assen, vest.adr. Australiëweg 4 9407TE Assen."
                  ]
                }
              ]
            }
          ]
        }
      ]
    },
    {
      "PublicerendeInstantieOmschrijving": "Rechtbank Oost-Brabant",
      "Locaties": [
        {
          "LocatiecodeLocatie": null,
          "Straat": "Leeghwaterlaan",
          "Huisnummer": "8",
          "HuisnummerToevoeging": null,
          "PlaatsNaam": null
        }
      ],
      "Publicatieclusters": [
        {
          "PublicatieclusterOmschrijving": "vereenvoudigde afwikkeling faillissementen",
          "Publicatiesoorten": [
            {
              "PublicatiesoortCaption": null,
              "PublicatiesNaarLocatie": [
                {
                  "LocatiecodeBekendmaking": null,
                  "Publicaties": [
                    "(F.01/16/214), Vinyflor Nederland B.V, vest.adr. Baltesakker 3 5625TC Eindhoven, KvK: 17056866. Cur: mr. S. Winkels-Koerselman, Postbus 253 5680AG BEST tel. 085-2010010. RC: mr. CAM de Bruijn."
                  ]
                }
              ]
            }
          ]
        },
        {
          "PublicatieclusterOmschrijving": "zittingen in schuldsaneringen",
          "Publicatiesoorten": [
            {
              "PublicatiesoortCaption": "beëindigingszitting",
              "PublicatiesNaarLocatie": [
                {
                  "LocatiecodeBekendmaking": null,
                  "Publicaties": [
                    "beëindigingszitting: op 10 september 2020 om 9:30 uur inzake (R.1/16/244) Oguz KÂHYA, woonadr. Admiraliteitslaan 422, 5224 EM 's-Hertogenbosch, geb. Emirdag 28 april 1971, voorheen hodn INSTALLATIEBEDRIJF O.K.. Bwv: A. van der Flier, Hulsenboschstraat 9, 4251 LR Werkendam, tel. 085-4880900.",
                    "beëindigingszitting: op 10 september 2020 om 9:30 uur inzake (R.1/16/245) Belkis KÂHYA, woonadr. Admiraliteitslaan 422, 5224 EM 's-Hertogenbosch, geb. Saint-Josse-ten-Noode (België) 23 september 1978. Bwv: A. van der Flier, Hulsenboschstraat 9, 4251 LR Werkendam, tel. 085-4880900.",
                    "beëindigingszitting: op 10 september 2020 om 9:30 uur inzake (R.1/17/199) Abdelmajid AMROUSSI, woonadr. Voltastraat 79, 5223 CK 's-Hertogenbosch, geb. El Jadida (Marokko) 15 maart 1975. Bwv: W.B.F. Mombarg, Postbus 2062, 3800 CB Amersfoort, tel. 088-7624225.",
                    "beëindigingszitting: op 10 september 2020 om 9:30 uur inzake (R.1/17/202) Albertus Adrianus VAN LITH, woonadr. Michiel de Ruyterstraat 9, 5224 GX 's-Hertogenbosch, geb. Zaltbommel 11 februari 1974. Bwv: F. Gevaert, Postbus 1400, 5602 BK Eindhoven, tel. 040-4006300.",
                    "beëindigingszitting: op 10 september 2020 om 9:30 uur inzake (R.1/17/203) Kim Johanna Theodora Wilhelmina KNORREN, woonadr. Nieuburgstraat 2, 5401 AD Uden, geb. Deurne (Nederland) 11 mei 1982. Bwv: J. van Rijen, Postbus 40251, 3504 AB Utrecht, tel. 030-6703054.",
                    "beëindigingszitting: op 10 september 2020 om 9:30 uur inzake (R.1/17/205) Jarla Edzelina van CORSTANJE, woonadr. Tempeliersdal 36, 5076 CL Haaren, geb. Leeuwarden (Nederland) 30 mei 1987. Bwv: mr. M.C.C. Ording, Postbus 2062, 3800 CB Amersfoort, tel. 088-7624225."
                  ]
                }
              ]
            },
            {
              "PublicatiesoortCaption": "verificatievergadering",
              "PublicatiesNaarLocatie": [
                {
                  "LocatiecodeBekendmaking": null,
                  "Publicaties": [
                    "verificatievergadering: pro forma op 10 september 2020 om 9:30 uur inzake (R.1/16/244) Oguz KÂHYA, woonadr. Admiraliteitslaan 422, 5224 EM 's-Hertogenbosch, geb. Emirdag 28 april 1971, voorheen hodn INSTALLATIEBEDRIJF O.K.. Bwv: A. van der Flier, Hulsenboschstraat 9, 4251 LR Werkendam, tel. 085-4880900.",
                    "verificatievergadering: pro forma op 10 september 2020 om 9:30 uur inzake (R.1/16/245) Belkis KÂHYA, woonadr. Admiraliteitslaan 422, 5224 EM 's-Hertogenbosch, geb. Saint-Josse-ten-Noode (België) 23 september 1978. Bwv: A. van der Flier, Hulsenboschstraat 9, 4251 LR Werkendam, tel. 085-4880900.",
                    "verificatievergadering: pro forma op 10 september 2020 om 9:30 uur inzake (R.1/17/199) Abdelmajid AMROUSSI, woonadr. Voltastraat 79, 5223 CK 's-Hertogenbosch, geb. El Jadida (Marokko) 15 maart 1975. Bwv: W.B.F. Mombarg, Postbus 2062, 3800 CB Amersfoort, tel. 088-7624225.",
                    "verificatievergadering: pro forma op 10 september 2020 om 9:30 uur inzake (R.1/17/202) Albertus Adrianus VAN LITH, woonadr. Michiel de Ruyterstraat 9, 5224 GX 's-Hertogenbosch, geb. Zaltbommel 11 februari 1974. Bwv: F. Gevaert, Postbus 1400, 5602 BK Eindhoven, tel. 040-4006300.",
                    "verificatievergadering: pro forma op 10 september 2020 om 9:30 uur inzake (R.1/17/203) Kim Johanna Theodora Wilhelmina KNORREN, woonadr. Nieuburgstraat 2, 5401 AD Uden, geb. Deurne (Nederland) 11 mei 1982. Bwv: J. van Rijen, Postbus 40251, 3504 AB Utrecht, tel. 030-6703054.",
                    "verificatievergadering: pro forma op 10 september 2020 om 9:30 uur inzake (R.1/17/205) Jarla Edzelina van CORSTANJE, woonadr. Tempeliersdal 36, 5076 CL Haaren, geb. Leeuwarden (Nederland) 30 mei 1987. Bwv: mr. M.C.C. Ording, Postbus 2062, 3800 CB Amersfoort, tel. 088-7624225."
                  ]
                }
              ]
            }
          ]
        },
        {
          "PublicatieclusterOmschrijving": "neerlegging slotuitdelingslijst in schuldsaneringen",
          "Publicatiesoorten": [
            {
              "PublicatiesoortCaption": null,
              "PublicatiesNaarLocatie": [
                {
                  "LocatiecodeBekendmaking": null,
                  "Publicaties": [
                    "met ingang van 31 augustus 2020 inzake (R.1/15/301) Sylvia Petra Mathilda HUP, woonadr. Dinkelstraat 142, 5704 GK Helmond, geb. Assen (Nederland) 08 maart 1985."
                  ]
                }
              ]
            }
          ]
        },
        {
          "PublicatieclusterOmschrijving": "einde schuldsaneringen",
          "Publicatiesoorten": [
            {
              "PublicatiesoortCaption": "met uitdeling en met schone lei",
              "PublicatiesNaarLocatie": [
                {
                  "LocatiecodeBekendmaking": null,
                  "Publicaties": [
                    "met uitdeling en met schone lei: op 22 mei 2020 inzake (R.1/18/94) Ingrid Johanna Mathea SLAATS, woonadr. Jacobsdreef 12, 5503 EH Veldhoven, geb. Eindhoven (Nederland) 09 september 1962."
                  ]
                }
              ]
            },
            {
              "PublicatiesoortCaption": "zonder uitdeling en met schone lei",
              "PublicatiesNaarLocatie": [
                {
                  "LocatiecodeBekendmaking": null,
                  "Publicaties": [
                    "zonder uitdeling en met schone lei: op 19 november 2019 inzake (R.1/16/280) Diana Huberdina Wilhelmina Catharina HAMAN, woonadr. Kootwijkstraat 3, 5651 AP Eindhoven, geb. Eindhoven 19 december 1979."
                  ]
                }
              ]
            }
          ]
        }
      ]
    },
    {
      "PublicerendeInstantieOmschrijving": "Rechtbank Rotterdam",
      "Locaties": [
        {
          "LocatiecodeLocatie": "Dordrecht",
          "Straat": "Steegoversloot",
          "Huisnummer": "36",
          "HuisnummerToevoeging": null,
          "PlaatsNaam": "Dordrecht"
        },
        {
          "LocatiecodeLocatie": "Rotterdam",
          "Straat": "Wilhelminaplein",
          "Huisnummer": "100-125",
          "HuisnummerToevoeging": null,
          "PlaatsNaam": "Rotterdam"
        }
      ],
      "Publicatieclusters": [
        {
          "PublicatieclusterOmschrijving": "uitspraken schuldsanering",
          "Publicatiesoorten": [
            {
              "PublicatiesoortCaption": null,
              "PublicatiesNaarLocatie": [
                {
                  "LocatiecodeBekendmaking": null,
                  "Publicaties": [
                    "op 03 augustus 2020 inzake (R.10/20/233) Edseline Lucretia Thadea Lakker, woonadr. Lodijk 67, 3079 TV Rotterdam, geb. Curaçao (Nederlandse Antillen) 15 maart 1962. Bwv: R. de Geus, Postbus 187, 3330 AD Zwijndrecht, tel. 078-7999944. RC: mr. W.J. Roos-van Toor.",
                    "Uitspraak schuldsanering op 03 augustus 2020 inzake (R.10/20/234) A. Stolk, woonadr. Klinkerlandsestraat 32 3249AL Herkingen, geb. Dirksland (Nederland) 23 juli 1961. hodn Holland Bakeries vest.adr. Leerlooier 7 E 9502KG Stadskanaal, KvK: 61460648 Bwv: mr W.P. Groenendijk, Postbus 324 3330AH ZWIJNDRECHT tel. 078-6125911. RC: mr. W.J. Roos-van Toor.",
                    "op 03 augustus 2020 inzake (R.10/20/235) Elisabeth Born, woonadr. Bernhardstraat 11, 3248 AC Melissant, geb. Zierikzee 22 augustus 1977. Bwv: T.P.F. Eisses, Postbus 187, 3330 AD Zwijndrecht, tel. 078-7999922. RC: mr. W.J. Roos-van Toor.",
                    "Uitspraak schuldsanering op 03 augustus 2020 inzake (R.10/20/236) S.B. Holder, woonadr. Leppedijk 80 3079GN Rotterdam, geb. Curaçao (Nederlandse Antillen) 08 oktober 1982. Bwv: J. Hoogland (Sociaal.nl Schuldsanering B.V.), Postbus 845 1440AV Purmerend tel. 088-7624200. RC: mr. W.J. Roos-van Toor.",
                    "Uitspraak schuldsanering op 03 augustus 2020 inzake (R.10/20/237) H.A. Margarittha, woonadr. Leppedijk 80 3079GN Rotterdam, geb. Curaçao (Nederlandse Antillen) 15 augustus 1979. Bwv: J. Hoogland (Sociaal.nl Schuldsanering B.V.), Postbus 845 1440AV Purmerend tel. 088-7624200. RC: mr. W.J. Roos-van Toor.",
                    "op 03 augustus 2020 inzake (R.10/20/238) Yusuf Saydam, woonadr. Narcissenstraat 117 A, 3073 CM Rotterdam, geb. Akdagmadeni (Turkije) 30 augustus 1986. Bwv: R. van den Brink, Postbus 68, 3214 ZH Zuidland, tel. 0181-699305. RC: mr. W.J. Roos-van Toor.",
                    "op 03 augustus 2020 inzake (R.10/20/239) Aart Anthonie Bakker, woonadr. Professor Teldersstraat 203, 3132 AW Vlaardingen, geb. Schiedam 21 juni 1963. Bwv: P.H.L. Adam, Postbus 7441, 3284 ZG Zuid-Beijerland, tel. 085-2738123. RC: mr. W.J. Roos-van Toor.",
                    "op 03 augustus 2020 inzake (R.10/20/240) Wilhelmina Hendrina Johanna Brons, woonadr. Professor Teldersstraat 203, 3132 AW Vlaardingen, geb. Vlaardingen 01 juni 1969. Bwv: P.H.L. Adam, Postbus 7441, 3284 ZG Zuid-Beijerland, tel. 085-2738123. RC: mr. W.J. Roos-van Toor."
                  ]
                }
              ]
            }
          ]
        },
        {
          "PublicatieclusterOmschrijving": "vereenvoudigde afwikkeling faillissementen",
          "Publicatiesoorten": [
            {
              "PublicatiesoortCaption": null,
              "PublicatiesNaarLocatie": [
                {
                  "LocatiecodeBekendmaking": null,
                  "Publicaties": [
                    "(F.10/19/104), Auto Trio B.V, corr.adr. Postbus 61.001 3002HA Rotterdam, vest.adr. Aelbrechtskade 148 3023JJ Rotterdam, vest.adr. Aelbrechtskade 150 3023JJ Rotterdam, KvK: 24080068 hodn Auto Trio Beheer corr.adr. Postbus 61.001 3002HA Rotterdam, vest.adr. Aelbrechtskade 148 -150 3023JJ Rotterdam. Cur: mr M. van der Laarse, Westerlaan 14 3016CK ROTTERDAM tel. 010-3133900. RC: mr. B.A. Cnossen."
                  ]
                }
              ]
            }
          ]
        },
        {
          "PublicatieclusterOmschrijving": "zittingen in schuldsaneringen",
          "Publicatiesoorten": [
            {
              "PublicatiesoortCaption": "verificatievergadering",
              "PublicatiesNaarLocatie": [
                {
                  "LocatiecodeBekendmaking": "Dordrecht",
                  "Publicaties": [
                    "verificatievergadering: pro forma op 08 september 2020 om 9:00 uur inzake (R.10/18/528) Andries Adrianus Quist, woonadr. Pieter de Hooghlaan 59, 3262 RD Oud-Beijerland, geb. Dordrecht 25 augustus 1987. Bwv: mr. L.E. de Wal, De Panoven 25, 4191 GW Geldermalsen, tel. 06-50945129."
                  ]
                },
                {
                  "LocatiecodeBekendmaking": "Rotterdam",
                  "Publicaties": [
                    "verificatievergadering: pro forma op 08 september 2020 om 9:00 uur inzake (R.10/17/577) Debby Mathilda Almeida, woonadr. Vuurplaat 105, 3071 AR Rotterdam, geb. Rotterdam 20 juni 1975. Bwv: M. Zomerdijk, Postbus 81145, 3009 GC Rotterdam, tel. 088-7624225.",
                    "verificatievergadering: pro forma op 08 september 2020 om 9:00 uur inzake (R.10/18/354) Abdelmalek Toumi, woonadr. Van Lennepstraat 220, 3027 RW Rotterdam, geb. Jeráda (Marokko) 02 juni 1983. Bwv: N. Pavljasevic, Postbus 187, 3330 AD Zwijndrecht, tel. 078-7999922."
                  ]
                }
              ]
            }
          ]
        },
        {
          "PublicatieclusterOmschrijving": "neerlegging slotuitdelingslijst in faillissementen",
          "Publicatiesoorten": [
            {
              "PublicatiesoortCaption": "met bepaling van vereenvoudigde afwikkeling",
              "PublicatiesNaarLocatie": [
                {
                  "LocatiecodeBekendmaking": "Dordrecht",
                  "Publicaties": [
                    "met bepaling van vereenvoudigde afwikkeling: met ingang van 01 september 2020 inzake (F.10/13/1214) BBN Diensten B.V., vest.adr. Biesland 17, 1948 RJ Beverwijk, KvK Enschede, 34059409, hodn PERSONEELSDIENSTEN DORDRECHT; voorheen hodn TRANSLIFT IJMOND B.V."
                  ]
                }
              ]
            }
          ]
        },
        {
          "PublicatieclusterOmschrijving": "einde faillissementen",
          "Publicatiesoorten": [
            {
              "PublicatiesoortCaption": "door verbindende uitdelingslijst",
              "PublicatiesNaarLocatie": [
                {
                  "LocatiecodeBekendmaking": null,
                  "Publicaties": [
                    "Door verbindende uitdelingslijst op 01 augustus 2020 inzake (F.10/16/631) HTM Infra Services B.V, vest.adr. Struitenweg 33 A 3082WR Rotterdam, KvK: 09082621."
                  ]
                }
              ]
            }
          ]
        },
        {
          "PublicatieclusterOmschrijving": "einde schuldsaneringen",
          "Publicatiesoorten": [
            {
              "PublicatiesoortCaption": "met uitdeling en met schone lei",
              "PublicatiesNaarLocatie": [
                {
                  "LocatiecodeBekendmaking": null,
                  "Publicaties": [
                    "met uitdeling en met schone lei: op 31 juli 2020 inzake (R.10/16/1025) Ali Ihsan Durkut, woonadr. Carnisselaan 106 B, 3083 HR Rotterdam, geb. Gemerek (Turkije) 30 november 1971.",
                    "met uitdeling en met schone lei: op 01 augustus 2020 inzake (R.10/17/137) Hassania El Moussati, woonadr. Molenpolder 156, 3453 NZ De Meern, geb. Temsamane (Marokko) 05 november 1973.",
                    "Einde schuldsanering met uitdeling en met schone lei op 01 augustus 2020 inzake (R.10/17/504) W.H. Pascha, woonadr. Lepelaarsingel 27 2903AH Capelle aan den IJssel, geb. Amsterdam (Nederland) 06 februari 1963.",
                    "Einde schuldsanering met uitdeling en met schone lei op 01 augustus 2020 inzake (R.10/17/509) M. Jabbar, woonadr. Schrijnwerkerstraat 46 4204GR Gorinchem, geb. district Suriname (Suriname) 07 januari 1969."
                  ]
                }
              ]
            },
            {
              "PublicatiesoortCaption": "met uitdeling en zonder schone lei",
              "PublicatiesNaarLocatie": [
                {
                  "LocatiecodeBekendmaking": null,
                  "Publicaties": [
                    "Einde schuldsanering met uitdeling en zonder schone lei op 01 augustus 2020 inzake (R.10/18/172) R.M. Elias, woonadr. van Bleiswijkstraat 56 D 3135AM Vlaardingen, geb. Curaçao (Nederlandse Antillen) 27 augustus 1987."
                  ]
                }
              ]
            }
          ]
        }
      ]
    },
    {
      "PublicerendeInstantieOmschrijving": "Rechtbank Zeeland-West-Brabant",
      "Locaties": [
        {
          "LocatiecodeLocatie": "Breda",
          "Straat": "Stationslaan",
          "Huisnummer": "10",
          "HuisnummerToevoeging": null,
          "PlaatsNaam": "Breda"
        },
        {
          "LocatiecodeLocatie": "Middelburg",
          "Straat": "Kousteensedijk",
          "Huisnummer": "2",
          "HuisnummerToevoeging": null,
          "PlaatsNaam": "Middelburg"
        }
      ],
      "Publicatieclusters": [
        {
          "PublicatieclusterOmschrijving": "vereenvoudigde afwikkeling faillissementen",
          "Publicatiesoorten": [
            {
              "PublicatiesoortCaption": null,
              "PublicatiesNaarLocatie": [
                {
                  "LocatiecodeBekendmaking": null,
                  "Publicaties": [
                    "(F.02/18/368), NEXZIE B.V, vest.adr. Goudstraat 7 7554NG Hengelo, KvK: 20134946 hodn NEXZIE B.V. corr.adr. Postbus 1.278 7550BG Hengelo Ov, vest.adr. Goudstraat 7 7554NG Hengelo. Cur: J.M. Molkenboer, Postbus 760 5000AT TILBURG tel. 013-5426093. RC: mr. M.D.E. Leppens."
                  ]
                }
              ]
            }
          ]
        },
        {
          "PublicatieclusterOmschrijving": "neerlegging slotuitdelingslijst in faillissementen",
          "Publicatiesoorten": [
            {
              "PublicatiesoortCaption": null,
              "PublicatiesNaarLocatie": [
                {
                  "LocatiecodeBekendmaking": "Breda",
                  "Publicaties": [
                    "Met ingang van 03 augustus 2020 inzake (F.02/15/49) Proavus B.V, vest.adr. Jacob van Ruisdaelstraat 116 3583CH Utrecht, KvK: 57953171 hodn Restaurant Mirabelle."
                  ]
                }
              ]
            }
          ]
        },
        {
          "PublicatieclusterOmschrijving": "einde faillissementen",
          "Publicatiesoorten": [
            {
              "PublicatiesoortCaption": "door goedkeuring akkoord",
              "PublicatiesNaarLocatie": [
                {
                  "LocatiecodeBekendmaking": null,
                  "Publicaties": [
                    "Door goedkeuring akkoord op 29 juli 2020 inzake (F.02/17/409) R. de Rooy, woonadr. Past van Beurdenstraat 74 5046HL Tilburg, geb. Goirle 20 februari 1967."
                  ]
                }
              ]
            }
          ]
        }
      ]
    }
  ],
  "Datum": "/Date(1596492000000)/"
}